Metadata-Version: 2.4
Name: baidu-openapi-client
Version: 0.1.0
Summary: 百度网盘 API 客户端
Author-email: Yin Nan <im.yinnan@gmail.com>
License: MIT
Classifier: License :: OSI Approved :: MIT License
Classifier: Operating System :: OS Independent
Classifier: Programming Language :: Python :: 3
Requires-Python: >=3.12
Requires-Dist: python-dateutil>=2.9.0.post0
Requires-Dist: urllib3>=2.4.0
